patchviz/__init__.py
patchviz/adversarial_patch.py
patchviz/data_loader.py
patchviz/examples.py
patchviz/explainer.py
patchviz/model_loader.py
patchviz/visualizer.py
patchviz-1.1.1.dist-info/LICENSE.txt
patchviz-1.1.1.dist-info/METADATA
patchviz-1.1.1.dist-info/WHEEL
patchviz-1.1.1.dist-info/top_level.txt
patchviz-1.1.1.dist-info/RECORD
