Metadata-Version: 2.1
Name: patchviz
Version: 1.1.1
Summary: Patch Viz: A library to test how well your model holds up against adversarial attacks
Home-page: https://github.com/suneel-nadipalli/patchviz
Author: Suneel Nadipalli
Author-email: nsuneel89@gmail.com
Classifier: Programming Language :: Python :: 3
Classifier: License :: OSI Approved :: MIT License
Classifier: Operating System :: OS Independent
Requires-Python: >=3.10
License-File: LICENSE.txt
Requires-Dist: torch
Requires-Dist: torchvision
Requires-Dist: torchaudio
Requires-Dist: numpy
Requires-Dist: matplotlib
Requires-Dist: captum
Requires-Dist: tqdm
